geojsonvt/__init__.py
geojsonvt/clip.py
geojsonvt/convert.py
geojsonvt/feature.py
geojsonvt/geojsonvt.py
geojsonvt/geometry.py
geojsonvt/simplify.py
geojsonvt/tile.py
geojsonvt/transform.py
geojsonvt/wrap.py
geojsonvt-0.1.0.dist-info/DESCRIPTION.rst
geojsonvt-0.1.0.dist-info/LICENSE.txt
geojsonvt-0.1.0.dist-info/METADATA
geojsonvt-0.1.0.dist-info/RECORD
geojsonvt-0.1.0.dist-info/WHEEL
geojsonvt-0.1.0.dist-info/metadata.json
geojsonvt-0.1.0.dist-info/top_level.txt
